s2p-1.0b18.data/purelib/bin/.dummy
s2p-1.0b18.data/purelib/bin/backflow
s2p-1.0b18.data/purelib/bin/bin2asc
s2p-1.0b18.data/purelib/bin/callTVL1.sh
s2p-1.0b18.data/purelib/bin/cldmask
s2p-1.0b18.data/purelib/bin/colormesh
s2p-1.0b18.data/purelib/bin/disp2ply
s2p-1.0b18.data/purelib/bin/disp_to_h
s2p-1.0b18.data/purelib/bin/downsa
s2p-1.0b18.data/purelib/bin/homography
s2p-1.0b18.data/purelib/bin/homwarp
s2p-1.0b18.data/purelib/bin/imprintf
s2p-1.0b18.data/purelib/bin/lsd
s2p-1.0b18.data/purelib/bin/mgm
s2p-1.0b18.data/purelib/bin/mgm_multi
s2p-1.0b18.data/purelib/bin/morphoop
s2p-1.0b18.data/purelib/bin/morsi
s2p-1.0b18.data/purelib/bin/plambda
s2p-1.0b18.data/purelib/bin/plyextrema
s2p-1.0b18.data/purelib/bin/pview
s2p-1.0b18.data/purelib/bin/qauto
s2p-1.0b18.data/purelib/bin/remove_small_cc
s2p-1.0b18.data/purelib/bin/synflow
s2p-1.0b18.data/purelib/bin/tvl1flow
s2p-1.0b18.data/purelib/bin/build_mgm_multi/CMakeCache.txt
s2p-1.0b18.data/purelib/bin/build_mgm_multi/Makefile
s2p-1.0b18.data/purelib/bin/build_mgm_multi/cmake_install.cmake
s2p-1.0b18.data/purelib/bin/build_mgm_multi/mgm
s2p-1.0b18.data/purelib/bin/build_mgm_multi/mgm_multi
s2p-1.0b18.data/purelib/bin/build_mgm_multi/CMakeFiles/CMakeDirectoryInformation.cmake
s2p-1.0b18.data/purelib/bin/build_mgm_multi/CMakeFiles/CMakeOutput.log
s2p-1.0b18.data/purelib/bin/build_mgm_multi/CMakeFiles/Makefile.cmake
s2p-1.0b18.data/purelib/bin/build_mgm_multi/CMakeFiles/Makefile2
s2p-1.0b18.data/purelib/bin/build_mgm_multi/CMakeFiles/TargetDirectories.txt
s2p-1.0b18.data/purelib/bin/build_mgm_multi/CMakeFiles/cmake.check_cache
s2p-1.0b18.data/purelib/bin/build_mgm_multi/CMakeFiles/feature_tests.bin
s2p-1.0b18.data/purelib/bin/build_mgm_multi/CMakeFiles/feature_tests.c
s2p-1.0b18.data/purelib/bin/build_mgm_multi/CMakeFiles/feature_tests.cxx
s2p-1.0b18.data/purelib/bin/build_mgm_multi/CMakeFiles/progress.marks
s2p-1.0b18.dist-info/METADATA
s2p-1.0b18.dist-info/RECORD
s2p-1.0b18.dist-info/WHEEL
s2p-1.0b18.dist-info/entry_points.txt
s2p-1.0b18.dist-info/top_level.txt
