Metadata-Version: 2.1
Name: s2p
Version: 1.0b18
Summary: Satellite Stereo Pipeline.
Home-page: https://github.com/cmla/s2p
License: UNKNOWN
Platform: UNKNOWN
Requires-Dist: numpy
Requires-Dist: scipy
Requires-Dist: rasterio[s3,test] (>=1.0.14)
Requires-Dist: utm
Requires-Dist: pyproj (>=2.0.2)
Requires-Dist: beautifulsoup4[lxml]
Requires-Dist: plyfile
Requires-Dist: ransac
Requires-Dist: rpcm (>=1.3)
Requires-Dist: requests
